spsdk_keyfactor/__init__.py
spsdk_keyfactor/provider.py
spsdk_keyfactor/__pyinstaller/__init__.py
spsdk_keyfactor/__pyinstaller/hook-spsdk_keyfactor.py
spsdk_keyfactor-0.3.0.dist-info/LICENSE
spsdk_keyfactor-0.3.0.dist-info/METADATA
spsdk_keyfactor-0.3.0.dist-info/WHEEL
spsdk_keyfactor-0.3.0.dist-info/entry_points.txt
spsdk_keyfactor-0.3.0.dist-info/top_level.txt
spsdk_keyfactor-0.3.0.dist-info/RECORD
