Metadata-Version: 2.1
Name: spsdk_keyfactor
Version: 0.3.0
Summary: SPSDK Signature Provider plugin using Keyfactor's API
Author: NXP
Maintainer-email: NXP <michal.starecek@nxp.com>
License: BSD-3-Clause
Project-URL: Homepage, https://github.com/nxp-mcuxpresso/spsdk_plugins/tree/master/keyfactor
Project-URL: Issues, https://github.com/nxp-mcuxpresso/spsdk_plugins/issues
Keywords: NXP,SPSDK,Keyfactor,Signature Provider
Classifier: Development Status :: 2 - Pre-Alpha
Classifier: Intended Audience :: Developers
Classifier: License :: OSI Approved :: BSD License
Classifier: Natural Language :: English
Classifier: Programming Language :: Python :: 3
Classifier: Programming Language :: Python :: 3.9
Classifier: Programming Language :: Python :: 3.10
Classifier: Programming Language :: Python :: 3.11
Classifier: Programming Language :: Python :: 3.12
Requires-Python: >=3.9
License-File: LICENSE
Requires-Dist: requests-pkcs12
Requires-Dist: python-dotenv
